pg_lo_storage/__init__.py
pg_lo_storage/fields.py
pg_lo_storage/storage.py
pg_lo_storage/views.py
pg_lo_storage-0.2.2.dist-info/licenses/LICENSE
pg_lo_storage-0.2.2.dist-info/METADATA
pg_lo_storage-0.2.2.dist-info/WHEEL
pg_lo_storage-0.2.2.dist-info/top_level.txt
pg_lo_storage-0.2.2.dist-info/RECORD
