Metadata-Version: 2.4
Name: pg-lo-storage
Version: 0.2.2
Summary: Use PostgreSQL large objects for file storage
License: MIT
Project-URL: Homepage, https://github.com/bibenga/pg-lo-storage
Project-URL: Issues, https://github.com/bibenga/pg-lo-storage/issues
Keywords: django
Classifier: Environment :: Web Environment
Classifier: Framework :: Django
Classifier: Intended Audience :: Developers
Classifier: License :: OSI Approved :: MIT License
Classifier: Operating System :: OS Independent
Classifier: Programming Language :: Python
Classifier: Programming Language :: Python :: 3
Classifier: Programming Language :: Python :: 3.12
Classifier: Programming Language :: Python :: 3.13
Classifier: Programming Language :: Python :: 3.14
Classifier: Topic :: Internet :: WWW/HTTP
Classifier: Topic :: System :: Distributed Computing
Classifier: Topic :: Software Development :: Libraries :: Python Modules
Requires-Python: >=3.12
License-File: LICENSE
Requires-Dist: django<7,>=5
Provides-Extra: test
Requires-Dist: pytest; extra == "test"
Requires-Dist: pytest-django; extra == "test"
Requires-Dist: pytest-mock; extra == "test"
Requires-Dist: psycopg[binary]; extra == "test"
Dynamic: license-file
